quilt/__init__.py
quilt/data.py
quilt/imports.py
quilt/nodes.py
quilt/team.py
quilt/util.py
quilt/asa/__init__.py
quilt/asa/img.py
quilt/asa/pytorch.py
quilt/test/__init__.py
quilt/test/gen_data.py
quilt/test/integration.py
quilt/test/test_asa_plot.py
quilt/test/test_asa_torch.py
quilt/test/test_build.py
quilt/test/test_checks.py
quilt/test/test_cli.py
quilt/test/test_command.py
quilt/test/test_gen_data.py
quilt/test/test_import.py
quilt/test/test_install.py
quilt/test/test_integration.py
quilt/test/test_push.py
quilt/test/test_signature.py
quilt/test/test_store.py
quilt/test/test_util.py
quilt/test/utils.py
quilt/tools/__init__.py
quilt/tools/build.py
quilt/tools/check_functions.py
quilt/tools/command.py
quilt/tools/compat.py
quilt/tools/const.py
quilt/tools/core.py
quilt/tools/data_transfer.py
quilt/tools/hashing.py
quilt/tools/main.py
quilt/tools/package.py
quilt/tools/sign.py
quilt/tools/store.py
quilt/tools/util.py
quilt-2.9.15.dist-info/DESCRIPTION.rst
quilt-2.9.15.dist-info/METADATA
quilt-2.9.15.dist-info/RECORD
quilt-2.9.15.dist-info/WHEEL
quilt-2.9.15.dist-info/entry_points.txt
quilt-2.9.15.dist-info/metadata.json
quilt-2.9.15.dist-info/top_level.txt
