Metadata-Version: 2.0
Name: quilt
Version: 2.9.15
Summary: Quilt is a data package manager
Home-page: https://github.com/quiltdata/quilt
Author: quiltdata
Author-email: contact@quiltdata.io
License: LICENSE
Download-URL: https://github.com/quiltdata/quilt/releases/tag/2.9.15
Keywords: quilt quiltdata shareable data dataframe package platform pandas
Platform: UNKNOWN
Classifier: Development Status :: 5 - Production/Stable
Classifier: Intended Audience :: Developers
Classifier: Operating System :: OS Independent
Classifier: Programming Language :: Python
Classifier: Programming Language :: Python :: 2.7
Classifier: Programming Language :: Python :: 3.5
Classifier: Programming Language :: Python :: 3.6
Requires-Dist: appdirs (>=1.4.0)
Requires-Dist: future (>=0.16.0)
Requires-Dist: numpy (>=1.14.0)
Requires-Dist: packaging (>=16.8)
Requires-Dist: pandas (>=0.21.0)
Requires-Dist: pyarrow (>=0.9.0)
Requires-Dist: pyyaml (>=3.12)
Requires-Dist: requests (>=2.12.4)
Requires-Dist: six (>=1.10.0)
Requires-Dist: tqdm (>=4.11.2)
Requires-Dist: xlrd (>=1.0.0)
Requires-Dist: enum34; python_version < "3.0"
Requires-Dist: pathlib2; python_version < "3.6"
Provides-Extra: img
Requires-Dist: Pillow (>=5.1.0); extra == 'img'
Requires-Dist: matplotlib (>=2.2.2); extra == 'img'
Provides-Extra: pytorch
Requires-Dist: torch (>=0.4.0); extra == 'pytorch'
Provides-Extra: tests
Requires-Dist: pytest (==3.3.2); extra == 'tests'
Requires-Dist: pytest-cov (==2.4.0); extra == 'tests'
Requires-Dist: responses (>=0.7.0); extra == 'tests'
Provides-Extra: tests
Requires-Dist: mock; python_version < "3.3" and extra == 'tests'
Provides-Extra: tests
Requires-Dist: funcsigs; python_version < "3.4" and extra == 'tests'
Provides-Extra: torchvision
Requires-Dist: torchvision (>=0.2.1); extra == 'torchvision'
